<?xml version="1.0" encoding="utf-8"?>

<ModMetaData>
  <name>[RS] CE: Less Sappers Please</name>
  <packageId>rs.celesssappersplease</packageId>
  <author>Shackleberry</author>
  <description>Reverts some changes from Combat Extended to reintroduce non-sapper raids.</description>
  <supportedVersions>
    <li>1.1</li>
    <li>1.2</li>
  </supportedVersions>
  <loadAfter>
    <li>CETeam.CombatExtended</li>
  </loadAfter>
  <modDependencies>
    <li>
      <packageId>CETeam.CombatExtended</packageId>
      <displayName>Combat Extended</displayName>
      <steamWorkshopUrl>steam://url/CommunityFilePage/1631756268</steamWorkshopUrl>
    </li>
  </modDependencies>
</ModMetaData>
